plotnine_prism/__init__.py
plotnine_prism/guide.py
plotnine_prism/pal.py
plotnine_prism/scale.py
plotnine_prism/schemes/_color_palettes.toml
plotnine_prism/schemes/_fill_palettes.toml
plotnine_prism/schemes/_shape_palettes.toml
plotnine_prism/schemes/autumn_leaves.toml
plotnine_prism/schemes/beer_and_ales.toml
plotnine_prism/schemes/black_and_white.toml
plotnine_prism/schemes/blueprint.toml
plotnine_prism/schemes/candy_bright.toml
plotnine_prism/schemes/candy_soft.toml
plotnine_prism/schemes/colorblind_safe.toml
plotnine_prism/schemes/colors.toml
plotnine_prism/schemes/diazo.toml
plotnine_prism/schemes/earth_tones.toml
plotnine_prism/schemes/evergreen.toml
plotnine_prism/schemes/fir.toml
plotnine_prism/schemes/flames.toml
plotnine_prism/schemes/floral.toml
plotnine_prism/schemes/greenwash.toml
plotnine_prism/schemes/inferno.toml
plotnine_prism/schemes/magma.toml
plotnine_prism/schemes/mustard_field.toml
plotnine_prism/schemes/muted_rainbow.toml
plotnine_prism/schemes/neon.toml
plotnine_prism/schemes/ocean.toml
plotnine_prism/schemes/office.toml
plotnine_prism/schemes/pastels.toml
plotnine_prism/schemes/pearl.toml
plotnine_prism/schemes/plasma.toml
plotnine_prism/schemes/prism_dark.toml
plotnine_prism/schemes/prism_light.toml
plotnine_prism/schemes/purple_passion.toml
plotnine_prism/schemes/quiet.toml
plotnine_prism/schemes/shades_of_gray.toml
plotnine_prism/schemes/spring.toml
plotnine_prism/schemes/stained_glass.toml
plotnine_prism/schemes/starry.toml
plotnine_prism/schemes/summer.toml
plotnine_prism/schemes/sunny_garden.toml
plotnine_prism/schemes/the_blues.toml
plotnine_prism/schemes/viridis.toml
plotnine_prism/schemes/warm_and_sunny.toml
plotnine_prism/schemes/warm_pastels.toml
plotnine_prism/schemes/waves.toml
plotnine_prism/schemes/winter_bright.toml
plotnine_prism/schemes/winter_soft.toml
plotnine_prism/schemes/wool_muffler.toml
plotnine_prism/theme.py
plotnine_prism/themeable.py
plotnine_prism-0.3.3.dist-info/METADATA
plotnine_prism-0.3.3.dist-info/WHEEL
plotnine_prism-0.3.3.dist-info/RECORD
