Metadata-Version: 2.3
Name: plotnine-prism
Version: 0.3.3
Summary: Prism themes for plotnine, inspired by ggprism
License: GNU General Public License v2.0
Author: pwwang
Author-email: pwwang@pwwang.com
Requires-Python: >=3.9,<4.0
Classifier: License :: Other/Proprietary License
Classifier: Programming Language :: Python :: 3
Classifier: Programming Language :: Python :: 3.9
Classifier: Programming Language :: Python :: 3.10
Classifier: Programming Language :: Python :: 3.11
Classifier: Programming Language :: Python :: 3.12
Classifier: Programming Language :: Python :: 3.13
Requires-Dist: diot[toml] (>=0.3,<0.4)
Requires-Dist: plotnine (>=0.12,<0.13)
